adi_env_parser/__init__.py
adi_env_parser/_console_parser.py
adi_env_parser/_parsers.py
adi_env_parser/_version.py
adi_env_parser/test_data/base.json
adi_env_parser/tests/parser_test.py
adi_env_parser-1.1.1.dist-info/LICENSE.md
adi_env_parser-1.1.1.dist-info/METADATA
adi_env_parser-1.1.1.dist-info/WHEEL
adi_env_parser-1.1.1.dist-info/entry_points.txt
adi_env_parser-1.1.1.dist-info/top_level.txt
adi_env_parser-1.1.1.dist-info/RECORD
