Metadata-Version: 2.1
Name: adi_env_parser
Version: 1.1.1
Summary: Adinsure Environment parser
Author-email: Jernej Kladnik <jernej.kladnik@adacta-fintech.com>
License: MIT License
Project-URL: homepage, https://github.com/adactafintech/environment-parser
Project-URL: documentation, https://github.com/adactafintech/environment-parser
Project-URL: repository, https://github.com/adactafintech/environment-parser
Classifier: Topic :: System :: Systems Administration
Classifier: Topic :: Utilities
Requires-Python: <4,>=3.8
License-File: LICENSE.md
Provides-Extra: build-local
Requires-Dist: setuptools >=45 ; extra == 'build-local'
Requires-Dist: setuptools-scm[toml] >=6.2 ; extra == 'build-local'
Requires-Dist: build ; extra == 'build-local'
Provides-Extra: dev
Requires-Dist: pre-commit ; extra == 'dev'
Requires-Dist: autopep8 ; extra == 'dev'
Requires-Dist: pytest ; extra == 'dev'
Provides-Extra: test
Requires-Dist: pytest ; extra == 'test'
